phoenix/__init__.py
phoenix/auth.py
phoenix/config.py
phoenix/datetime_utils.py
phoenix/exceptions.py
phoenix/py.typed
phoenix/services.py
phoenix/settings.py
phoenix/version.py
phoenix/__generated__/__init__.py
phoenix/__generated__/classification_evaluator_configs/__init__.py
phoenix/__generated__/classification_evaluator_configs/_correctness_classification_evaluator_config.py
phoenix/__generated__/classification_evaluator_configs/_document_relevance_classification_evaluator_config.py
phoenix/__generated__/classification_evaluator_configs/_faithfulness_classification_evaluator_config.py
phoenix/__generated__/classification_evaluator_configs/_hallucination_classification_evaluator_config.py
phoenix/__generated__/classification_evaluator_configs/_models.py
phoenix/__generated__/classification_evaluator_configs/_tool_invocation_classification_evaluator_config.py
phoenix/__generated__/classification_evaluator_configs/_tool_selection_classification_evaluator_config.py
phoenix/core/__init__.py
phoenix/core/embedding_dimension.py
phoenix/core/model.py
phoenix/core/model_schema.py
phoenix/core/model_schema_adapter.py
phoenix/db/README.md
phoenix/db/__init__.py
phoenix/db/alembic.ini
phoenix/db/bulk_inserter.py
phoenix/db/constants.py
phoenix/db/engines.py
phoenix/db/enums.py
phoenix/db/facilitator.py
phoenix/db/helpers.py
phoenix/db/iam_auth.py
phoenix/db/migrate.py
phoenix/db/models.py
phoenix/db/pg_config.py
phoenix/db/insertion/__init__.py
phoenix/db/insertion/constants.py
phoenix/db/insertion/dataset.py
phoenix/db/insertion/document_annotation.py
phoenix/db/insertion/evaluation.py
phoenix/db/insertion/helpers.py
phoenix/db/insertion/session_annotation.py
phoenix/db/insertion/span.py
phoenix/db/insertion/span_annotation.py
phoenix/db/insertion/trace_annotation.py
phoenix/db/insertion/types.py
phoenix/db/migrations/__init__.py
phoenix/db/migrations/env.py
phoenix/db/migrations/script.py.mako
phoenix/db/migrations/data_migration_scripts/__init__.py
arize_phoenix-12.33.1.dist-info/METADATA
arize_phoenix-12.33.1.dist-info/WHEEL
arize_phoenix-12.33.1.dist-info/entry_points.txt
arize_phoenix-12.33.1.dist-info/licenses/IP_NOTICE
arize_phoenix-12.33.1.dist-info/licenses/LICENSE
arize_phoenix-12.33.1.dist-info/RECORD
