Metadata-Version: 2.4
Name: arize-phoenix
Version: 12.33.1
Summary: AI Observability and Evaluation
Project-URL: Documentation, https://arize.com/docs/phoenix/
Project-URL: Issues, https://github.com/Arize-ai/phoenix/issues
Project-URL: Source, https://github.com/Arize-ai/phoenix
Author-email: Arize AI <phoenix-devs@arize.com>
License: Elastic-2.0
License-File: IP_NOTICE
License-File: LICENSE
Keywords: Explainability,Monitoring,Observability
Classifier: Programming Language :: Python
Classifier: Programming Language :: Python :: 3.10
Classifier: Programming Language :: Python :: 3.11
Classifier: Programming Language :: Python :: 3.12
Classifier: Programming Language :: Python :: 3.13
Requires-Python: <3.14,>=3.10
Requires-Dist: aioitertools
Requires-Dist: aiosqlite
Requires-Dist: alembic<2,>=1.3.0
Requires-Dist: arize-phoenix-client>=1.28.0
Requires-Dist: arize-phoenix-evals>=2.8.0
Requires-Dist: arize-phoenix-otel>=0.14.0
Requires-Dist: authlib
Requires-Dist: cachetools
Requires-Dist: email-validator
Requires-Dist: fastapi
Requires-Dist: grpc-interceptor
Requires-Dist: grpcio
Requires-Dist: httpx
Requires-Dist: jinja2
Requires-Dist: jmespath
Requires-Dist: ldap3
Requires-Dist: numpy!=2.0.0
Requires-Dist: openinference-instrumentation>=0.1.32
Requires-Dist: openinference-semantic-conventions>=0.1.20
Requires-Dist: opentelemetry-exporter-otlp
Requires-Dist: opentelemetry-proto>=1.12.0
Requires-Dist: opentelemetry-sdk
Requires-Dist: opentelemetry-semantic-conventions
Requires-Dist: orjson
Requires-Dist: pandas>=1.0
Requires-Dist: prometheus-client
Requires-Dist: protobuf>=4.25.8
Requires-Dist: psutil
Requires-Dist: pyarrow
Requires-Dist: pydantic>=2.1.0
Requires-Dist: python-dateutil
Requires-Dist: python-multipart
Requires-Dist: scikit-learn
Requires-Dist: scipy
Requires-Dist: sqlalchemy[asyncio]<3,>=2.0.4
Requires-Dist: sqlean-py<3.50,>=3.45.1; platform_system == 'Windows'
Requires-Dist: sqlean-py>=3.45.1; platform_system != 'Windows'
Requires-Dist: starlette
Requires-Dist: strawberry-graphql==0.287.3
Requires-Dist: tqdm
Requires-Dist: typing-extensions>=4.6
Requires-Dist: uvicorn
Requires-Dist: wrapt<2,>=1.17.2
Provides-Extra: aws
Requires-Dist: boto3; extra == 'aws'
Provides-Extra: container
Requires-Dist: aiohttp; extra == 'container'
Requires-Dist: anthropic>=0.49.0; extra == 'container'
Requires-Dist: azure-identity; extra == 'container'
Requires-Dist: boto3; extra == 'container'
Requires-Dist: fast-hdbscan>=0.2.0; extra == 'container'
Requires-Dist: google-genai; (python_version < '3.10') and extra == 'container'
Requires-Dist: google-genai>=1.50.0; (python_version >= '3.10') and extra == 'container'
Requires-Dist: numba>=0.60.0; extra == 'container'
Requires-Dist: openai>=1.0.0; extra == 'container'
Requires-Dist: opentelemetry-exporter-otlp==1.39.1; extra == 'container'
Requires-Dist: opentelemetry-instrumentation-fastapi==0.60b1; extra == 'container'
Requires-Dist: opentelemetry-instrumentation-grpc==0.60b1; extra == 'container'
Requires-Dist: opentelemetry-instrumentation-sqlalchemy==0.60b1; extra == 'container'
Requires-Dist: opentelemetry-proto==1.39.1; extra == 'container'
Requires-Dist: opentelemetry-sdk==1.39.1; extra == 'container'
Requires-Dist: opentelemetry-semantic-conventions==0.60b1; extra == 'container'
Requires-Dist: prometheus-client; extra == 'container'
Requires-Dist: py-grpc-prometheus; extra == 'container'
Requires-Dist: strawberry-graphql[opentelemetry]==0.287.3; extra == 'container'
Requires-Dist: umap-learn; extra == 'container'
Requires-Dist: uvloop; (platform_system != 'Windows') and extra == 'container'
Provides-Extra: embeddings
Requires-Dist: fast-hdbscan>=0.2.0; extra == 'embeddings'
Requires-Dist: numba>=0.60.0; extra == 'embeddings'
Requires-Dist: umap-learn; extra == 'embeddings'
Provides-Extra: evals
Provides-Extra: experimental
Provides-Extra: pg
Requires-Dist: asyncpg; extra == 'pg'
Requires-Dist: psycopg[binary,pool]; extra == 'pg'
Provides-Extra: test
